{
	"info": {
		"_postman_id": "aa3607c2-fd9f-4b24-b996-b08b3b279480",
		"name": "react",
		"schema": "https://schema.getpostman.com/json/collection/v2.1.0/collection.json"
	},
	"item": [
		{
			"name": "请求列表",
			"request": {
				"method": "GET",
				"header": [],
				"url": {
					"raw": "http://localhost:5000/manage/category/list?parentId=0",
					"protocol": "http",
					"host": [
						"120",
						"55",
						"193",
						"14"
					],
					"port": "5000",
					"path": [
						"manage",
						"category",
						"list"
					],
					"query": [
						{
							"key": "parentId",
							"value": "0"
						}
					]
				}
			},
			"response": []
		},
		{
			"name": "请求天气",
			"request": {
				"method": "GET",
				"header": [],
				"url": {
					"raw": "restapi.amap.com/v3/weather/weatherInfo?key=98c97d10c1fda37bdc5402d15c1cdd71&city=北京",
					"host": [
						"restapi",
						"amap",
						"com"
					],
					"path": [
						"v3",
						"weather",
						"weatherInfo"
					],
					"query": [
						{
							"key": "key",
							"value": "98c97d10c1fda37bdc5402d15c1cdd71"
						},
						{
							"key": "city",
							"value": "北京"
						}
					]
				}
			},
			"response": []
		},
		{
			"name": "添加商品类别",
			"request": {
				"method": "POST",
				"header": [
					{
						"key": "Content-Type",
						"value": "application/x-www-form-urlencoded"
					}
				],
				"body": {
					"mode": "urlencoded",
					"urlencoded": [
						{
							"key": "categoryName",
							"value": "111级分类",
							"type": "text"
						},
						{
							"key": "parentId",
							"value": "0",
							"type": "text"
						}
					]
				},
				"url": {
					"raw": "http://localhost:5000/manage/category/add",
					"protocol": "http",
					"host": [
						"localhost"
					],
					"port": "5000",
					"path": [
						"manage",
						"category",
						"add"
					]
				}
			},
			"response": []
		},
		{
			"name": "请求二级列表 ",
			"request": {
				"method": "GET",
				"header": [],
				"url": {
					"raw": "http://localhost:5000/manage/category/list?parentId=0",
					"protocol": "http",
					"host": [
						"localhost"
					],
					"port": "5000",
					"path": [
						"manage",
						"category",
						"list"
					],
					"query": [
						{
							"key": "parentId",
							"value": "0"
						}
					]
				}
			},
			"response": []
		},
		{
			"name": "更新列表",
			"request": {
				"method": "POST",
				"header": [],
				"body": {
					"mode": "formdata",
					"formdata": []
				},
				"url": {
					"raw": "http://localhost:5000/manage/category/update",
					"protocol": "http",
					"host": [
						"localhost"
					],
					"port": "5000",
					"path": [
						"manage",
						"category",
						"update"
					]
				}
			},
			"response": []
		},
		{
			"name": "请求商品分页列表",
			"event": [
				{
					"listen": "prerequest",
					"script": {
						"type": "text/javascript",
						"exec": [
							"pageNum=1&pageSize=5"
						]
					}
				}
			],
			"request": {
				"method": "GET",
				"header": [],
				"url": {
					"raw": "http://120.55.193.14:5000/manage/product/list",
					"protocol": "http",
					"host": [
						"120",
						"55",
						"193",
						"14"
					],
					"port": "5000",
					"path": [
						"manage",
						"product",
						"list"
					]
				}
			},
			"response": []
		},
		{
			"name": "搜索商品",
			"request": {
				"method": "GET",
				"header": [],
				"url": {
					"raw": "http://localhost:5000/manage/product/search?productDesc=1&pageNum=1&pageSize=2",
					"protocol": "http",
					"host": [
						"localhost"
					],
					"port": "5000",
					"path": [
						"manage",
						"product",
						"search"
					],
					"query": [
						{
							"key": "productDesc",
							"value": "1"
						},
						{
							"key": "pageNum",
							"value": "1"
						},
						{
							"key": "pageSize",
							"value": "2"
						}
					]
				}
			},
			"response": []
		},
		{
			"name": "根据分类id获取分类",
			"request": {
				"method": "GET",
				"header": [],
				"url": {
					"raw": "http://localhost:5000/manage/catogory/info?categoryId=101",
					"protocol": "http",
					"host": [
						"localhost"
					],
					"port": "5000",
					"path": [
						"manage",
						"catogory",
						"info"
					],
					"query": [
						{
							"key": "categoryId",
							"value": "101"
						}
					]
				}
			},
			"response": []
		},
		{
			"name": "更新商品状态",
			"request": {
				"method": "POST",
				"header": [
					{
						"key": "Content-Type",
						"value": "application/x-www-form-urlencoded"
					}
				],
				"body": {
					"mode": "urlencoded",
					"urlencoded": [
						{
							"key": "productId",
							"value": "",
							"type": "text"
						},
						{
							"key": "status",
							"value": "",
							"type": "text"
						}
					]
				},
				"url": {
					"raw": "http://localhost:5000/manage/product/updateStatus",
					"protocol": "http",
					"host": [
						"localhost"
					],
					"port": "5000",
					"path": [
						"manage",
						"product",
						"updateStatus"
					]
				}
			},
			"response": []
		},
		{
			"name": "添加商品",
			"request": {
				"method": "POST",
				"header": [
					{
						"key": "Content-Type",
						"value": "application/x-www-form-urlencoded"
					}
				],
				"body": {
					"mode": "urlencoded",
					"urlencoded": [
						{
							"key": "categoryId",
							"value": "",
							"type": "text"
						},
						{
							"key": "pCategoryId",
							"value": "",
							"type": "text"
						},
						{
							"key": "name",
							"value": "",
							"type": "text"
						},
						{
							"key": "price",
							"value": "",
							"type": "text"
						},
						{
							"key": "desc",
							"value": "",
							"type": "text"
						}
					]
				},
				"url": {
					"raw": "http://localhost:5000/manage/product/add",
					"protocol": "http",
					"host": [
						"localhost"
					],
					"port": "5000",
					"path": [
						"manage",
						"product",
						"add"
					]
				}
			},
			"response": []
		},
		{
			"name": "上传图片",
			"request": {
				"method": "POST",
				"header": [
					{
						"key": "Content-Type",
						"value": "application/x-www-form-urlencoded"
					}
				],
				"body": {
					"mode": "formdata",
					"formdata": [
						{
							"key": "img",
							"type": "file",
							"src": "002.jpg"
						}
					]
				},
				"url": {
					"raw": "http://localhost:5000/manage/img/upload",
					"protocol": "http",
					"host": [
						"localhost"
					],
					"port": "5000",
					"path": [
						"manage",
						"img",
						"upload"
					]
				}
			},
			"response": []
		},
		{
			"name": "删除图片",
			"request": {
				"method": "POST",
				"header": [
					{
						"key": "Content-Type",
						"value": "application/x-www-form-urlencoded"
					}
				],
				"body": {
					"mode": "formdata",
					"formdata": [
						{
							"key": "img",
							"value": "image-1615381890653.jpg",
							"type": "text"
						}
					]
				},
				"url": {
					"raw": "http://localhost:5000/manage/img/delete",
					"protocol": "http",
					"host": [
						"localhost"
					],
					"port": "5000",
					"path": [
						"manage",
						"img",
						"delete"
					]
				}
			},
			"response": []
		},
		{
			"name": "更新商品",
			"request": {
				"method": "POST",
				"header": [
					{
						"key": "Content-Type",
						"value": "application/x-www-form-urlencoded"
					}
				],
				"body": {
					"mode": "urlencoded",
					"urlencoded": [
						{
							"key": "categoryId",
							"value": "",
							"type": "text"
						},
						{
							"key": "pCategoryId",
							"value": "",
							"type": "text"
						},
						{
							"key": "name",
							"value": "",
							"type": "text"
						},
						{
							"key": "price",
							"value": "",
							"type": "text"
						},
						{
							"key": "desc",
							"value": "",
							"type": "text"
						},
						{
							"key": "_id",
							"value": "",
							"type": "text"
						}
					]
				},
				"url": {
					"raw": "http://localhost:5000/manage/product/update",
					"protocol": "http",
					"host": [
						"localhost"
					],
					"port": "5000",
					"path": [
						"manage",
						"product",
						"update"
					]
				}
			},
			"response": []
		},
		{
			"name": "获取角色列表",
			"request": {
				"method": "GET",
				"header": [],
				"url": {
					"raw": "http://localhost:5000/manage/role/list",
					"protocol": "http",
					"host": [
						"localhost"
					],
					"port": "5000",
					"path": [
						"manage",
						"role",
						"list"
					]
				}
			},
			"response": []
		},
		{
			"name": "获取用户列表",
			"request": {
				"method": "GET",
				"header": [],
				"url": {
					"raw": "http://localhost:5000/manage/user/list",
					"protocol": "http",
					"host": [
						"localhost"
					],
					"port": "5000",
					"path": [
						"manage",
						"user",
						"list"
					]
				}
			},
			"response": []
		},
		{
			"name": "添加角色",
			"request": {
				"method": "POST",
				"header": [
					{
						"key": "Content-Type",
						"value": "application/x-www-form-urlencoded"
					}
				],
				"body": {
					"mode": "urlencoded",
					"urlencoded": [
						{
							"key": "roleName",
							"value": "roleNam",
							"type": "text"
						}
					]
				},
				"url": {
					"raw": "http://localhost:5000/manage/role/add",
					"protocol": "http",
					"host": [
						"localhost"
					],
					"port": "5000",
					"path": [
						"manage",
						"role",
						"add"
					]
				}
			},
			"response": []
		},
		{
			"name": "更新权限",
			"request": {
				"method": "POST",
				"header": [
					{
						"key": "Content-Type",
						"value": "application/x-www-form-urlencoded"
					}
				],
				"body": {
					"mode": "urlencoded",
					"urlencoded": [
						{
							"key": "roleName",
							"value": "roleNam",
							"type": "text"
						},
						{
							"key": "_id",
							"value": "604c32a7ff646469005f9f44",
							"type": "text"
						},
						{
							"key": "auth_name",
							"value": "1111",
							"type": "text"
						},
						{
							"key": "menus",
							"value": "/category",
							"type": "text"
						},
						{
							"key": "menus",
							"value": "/home",
							"type": "text"
						},
						{
							"key": "auth_name",
							"value": "",
							"type": "text",
							"disabled": true
						}
					]
				},
				"url": {
					"raw": "http://localhost:5000/manage/role/update",
					"protocol": "http",
					"host": [
						"localhost"
					],
					"port": "5000",
					"path": [
						"manage",
						"role",
						"update"
					]
				}
			},
			"response": []
		},
		{
			"name": "删除一个用户",
			"request": {
				"method": "POST",
				"header": [
					{
						"key": "Content-Type",
						"value": "application/x-www-form-urlencoded"
					}
				],
				"body": {
					"mode": "urlencoded",
					"urlencoded": [
						{
							"key": "userId",
							"value": "",
							"type": "text"
						}
					]
				},
				"url": {
					"raw": "http://localhost:5000/manage/user/delete",
					"protocol": "http",
					"host": [
						"localhost"
					],
					"port": "5000",
					"path": [
						"manage",
						"user",
						"delete"
					]
				}
			},
			"response": []
		},
		{
			"name": "添加用户",
			"request": {
				"method": "POST",
				"header": [
					{
						"key": "Content-Type",
						"value": "application/x-www-form-urlencoded"
					}
				],
				"body": {
					"mode": "urlencoded",
					"urlencoded": [
						{
							"key": "username",
							"value": "",
							"type": "text"
						},
						{
							"key": "password",
							"value": "",
							"type": "text"
						},
						{
							"key": "phone",
							"value": "",
							"type": "text"
						},
						{
							"key": "",
							"value": "",
							"type": "text"
						}
					]
				},
				"url": {
					"raw": "http://localhost:5000/manage/user/add",
					"protocol": "http",
					"host": [
						"localhost"
					],
					"port": "5000",
					"path": [
						"manage",
						"user",
						"add"
					]
				}
			},
			"response": []
		},
		{
			"name": "添加商品类别",
			"request": {
				"method": "POST",
				"header": [
					{
						"key": "Content-Type",
						"value": "application/x-www-form-urlencoded"
					}
				],
				"body": {
					"mode": "urlencoded",
					"urlencoded": [
						{
							"key": "categoryName",
							"value": "111级分类",
							"type": "text"
						},
						{
							"key": "parentId",
							"value": "0",
							"type": "text"
						}
					]
				},
				"url": {
					"raw": "http://localhost:5000/manage/category/add",
					"protocol": "http",
					"host": [
						"localhost"
					],
					"port": "5000",
					"path": [
						"manage",
						"category",
						"add"
					]
				}
			},
			"response": []
		}
	]
}